scope/__init__.py
scope_py-0.1.1.dist-info/LICENSE
scope_py-0.1.1.dist-info/WHEEL
scope_py-0.1.1.dist-info/METADATA
scope_py-0.1.1.dist-info/RECORD
